{
    "title": "Default Editor",
    "layoutRoot": "root",
    "containers": {
        "root": {
            "id": "1",
            "type": "split",
            "orientation": "horizontal",
            "children": [
                {
                    "containerId": "header",
                    "size": { "initial": { "value": 50, "unit": "px", "type": "fixed" }}
                },
                {
                    "containerId": "mainBody",
                    "size": { "initial": { "type": "fill" }}
                },
                {
                    "containerId": "footer",
                    "size": { "initial": { "value": 50, "unit": "px", "type": "fixed" }}
                }
            ]
        },
        "header": {
            "id": "2",
            "background": "#007acc"
        },
        "mainBody": {
            "id": "3",
            "background": "#3c3c3c",
            "type": "split",
            "orientation": "vertical",
            "children": [
                {
                    "containerId": "editor1",
                    "size": { "initial": { "type": "fill" }}
                },
                {
                    "containerId": "editor2",
                    "size": { "initial": { "type": "fill" }}
                }
            ]
        },
        "footer": {
            "id": "4",
            "background": "#007acc"
        },
        "editor1": {
            "id": "5",
            "background": "#222222"
        },
        "editor2": {
            "id": "6",
            "background": "#444444"
        }
    }
}